[
  {
    "name": "Sarah Mitchell",
    "email": "sarah.mitchell@techcorp.com",
    "age": 34,
    "city": "Seattle",
    "occupation": "Software Engineer"
  },
  {
    "name": "James Rodriguez",
    "email": "james.rodriguez@innovate.io",
    "age": 42,
    "city": "Austin",
    "occupation": "Product Manager"
  },
  {
    "name": "Emily Chen",
    "email": "emily.chen@dataservices.com",
    "age": 29,
    "city": "San Francisco",
    "occupation": "Data Scientist"
  },
  {
    "name": "Michael O'Brien",
    "email": "michael.obrien@consulting.net",
    "age": 51,
    "city": "Boston",
    "occupation": "Business Analyst"
  },
  {
    "name": "Priya Patel",
    "email": "priya.patel@cloudtech.com",
    "age": 38,
    "city": "New York",
    "occupation": "DevOps Engineer"
  }
]
